CHANGELOG.md
mypycounts/__init__.py
mypycounts/data/__init__.py
mypycounts/data/flatland.txt
mypycounts/datasets.py
mypycounts/mypycounts.py
mypycounts/plotting.py
tests/einstein.txt
tests/test_mypycounts.py
mypycounts-0.2.0.dist-info/LICENSE
mypycounts-0.2.0.dist-info/METADATA
mypycounts-0.2.0.dist-info/WHEEL
mypycounts-0.2.0.dist-info/RECORD
