Metadata-Version: 2.1
Name: mypycounts
Version: 0.2.0
Summary: A package for counting words and others.
License: MIT
Author: Emmanuel Arkoh-Nelson
Requires-Python: >=3.9
Classifier: License :: OSI Approved :: MIT License
Classifier: Programming Language :: Python :: 3
Classifier: Programming Language :: Python :: 3.9
Classifier: Programming Language :: Python :: 3.10
Classifier: Programming Language :: Python :: 3.11
Classifier: Programming Language :: Python :: 3.12
Requires-Dist: click-option-group ; python_version >= "3.9" and python_version < "4"
Requires-Dist: matplotlib (>=3.8.4)
